apollog/__init__.py
apollog/cli.py
apollog/cloudformation_template.yaml
apollog-0.1.1.data/scripts/apollog.bat
apollog-0.1.1.data/scripts/apollog_cli.py
apollog-0.1.1.dist-info/METADATA
apollog-0.1.1.dist-info/WHEEL
apollog-0.1.1.dist-info/entry_points.txt
apollog-0.1.1.dist-info/top_level.txt
apollog-0.1.1.dist-info/RECORD
