Metadata-Version: 2.4
Name: apollog
Version: 0.1.1
Summary: A monitoring solution for AWS services with log aggregation and error event summarization
Home-page: https://github.com/Bhavinrathava/Apollog
Author: Apollog Team
Author-email: author@example.com
Classifier: Programming Language :: Python :: 3
Classifier: License :: OSI Approved :: MIT License
Classifier: Operating System :: OS Independent
Requires-Python: >=3.8
Requires-Dist: boto3>=1.26.0
Requires-Dist: botocore
Requires-Dist: PyYAML
Dynamic: author
Dynamic: author-email
Dynamic: classifier
Dynamic: description
Dynamic: description-content-type
Dynamic: home-page
Dynamic: requires-dist
Dynamic: requires-python
Dynamic: summary
